evrima/__init__.py
evrima/rcon/__init__.py
evrima/rcon/client.py
evrima/rcon/exceptions.py
evrima/rcon/helpers.py
evrima/rcon/models.py
evrima_py-0.3.1.dist-info/licenses/LICENSE
evrima_py-0.3.1.dist-info/METADATA
evrima_py-0.3.1.dist-info/WHEEL
evrima_py-0.3.1.dist-info/top_level.txt
evrima_py-0.3.1.dist-info/RECORD
